[{"8": 8, " ": 60, "\u6708": 3, "2": 2, "\u65e5": 3, "\uff0c": 48, "\u7f51": 4, "\u6599": 2, "\u79f0": 3, "\u534e": 5, "\u4f4f": 8, "\u96c6": 5, "\u56e2": 3, "\u65d7": 2, "\u4e0b": 5, "\u9152": 5, "\u5e97": 5, "\u7528": 6, "\u6237": 4, "\u6570": 7, "\u636e": 7, "\u7591": 2, "\u4f3c": 2, "\u53d1": 6, "\u751f": 3, "\u6cc4": 3, "\u9732": 3, "\u3002": 22, "\u5356": 2, "\u5bb6": 4, "\u7684": 34, "\u5185": 2, "\u770b": 3, "\u5305": 3, "\u3001": 13, "\u7b49": 5, "1": 14, "0": 8, "\u4e2a": 5, "\u5ba2": 2, "\u4fe1": 4, "\u606f": 5, "\u6ce8": 3, "\u5165": 6, "\u767b": 2, "\u8bb0": 2, "\u8eab": 2, "\u4efd": 2, "\u5f00": 4, "\u5f55": 2, "\u53f7": 3, "\u8bc1": 2, "\u5bf9": 9, "\u8fd9": 3, "\u7ea6": 3, "5": 11, "\u6761": 2, "\u6253": 5, "\u51fa": 5, "\u552e": 2, "\u7b2c": 2, "\u4e09": 2, "\u65b9": 4, "\u63d0": 2, "\u8fdb": 3, "\u884c": 5, "\u9a8c": 2, "\u4e3a": 5, "\u771f": 2, "\u5b9e": 3, "\u6027": 2, "\u9ad8": 2, "\u5f53": 2, "\u660e": 5, "\u5df2": 2, "\u5728": 7, "\u5c55": 2, "\u67e5": 3, "\u4e00": 10, "\u65f6": 3, "\u95f4": 3, "\u62a5": 2, "\u8b66": 3, "\u4e0a": 7, "\u6d77": 3, "\u5230": 3, "\u4ecb": 2, "\u4f53": 2, "\u5317": 2, "\u4eac": 2, "6": 2, "N": 3, "B": 2, "A": 2, "\u4e2d": 16, "\u56fd": 16, "\u8d5b": 2, "\u5e7f": 4, "\u5dde": 4, "\u7ad9": 4, "\u5982": 3, ",": 4, "\u706b": 8, "\u7bad": 8, "\u518d": 4, "\u6b21": 4, "\u80dc": 8, "\u4ee5": 7, "9": 4, "-": 6, "\u51fb": 4, "\u8d25": 2, "\u7bee": 4, "\u59da": 4, "\u6e10": 2, "\u4f73": 2, "\u5883": 2, "\u4e86": 2, "\u5206": 11, "3": 2, "\u79d2": 2, "\u6295": 2, "\u62ff": 2, "\u677f": 4, "\u4ed6": 2, "\u8fd8": 2, "\u76d6": 2, "\u5e3d": 2, "\u4e24": 5, "\u6218": 6, "\u7686": 4, "\u7ee9": 2, "\u5706": 2, "\u6ee1": 2, "\u7ed3": 3, "\u675f": 2, "\u76f4": 2, "\uff1a": 2, "\u201c": 2, "\u6211": 8, "\u548c": 8, "\u7956": 8, "\u523b": 2, "\u4e5f": 5, "\u4e0d": 3, "\u80fd": 2, "\u5272": 2, "\u2026": 4, "\u201d": 2, "\u5143": 2, "\u65e6": 2, "\u524d": 2, "\u5915": 2, "\u535a": 2, "\u7269": 2, "\u9986": 2, "\u592e": 4, "\u89c6": 6, "\u4e3b": 7, "\u64ad": 4, "\u5eb7": 2, "\u8f89": 2, "\u971e": 2, "\u5965": 4, "\u8fd0": 4, "\u5065": 4, "\u513f": 4, "\u5085": 2, "\u56ed": 2, "\u6167": 2, "\u82cf": 2, "\u70b3": 2, "\u6dfb": 2, "\u540c": 4, "\u5531": 2, "\u54cd": 2, "\u300a": 2, "\u300b": 2, "\u5411": 4, "\u732e": 4, "\u6700": 2, "\u6df1": 4, "\u60c5": 4, "\u544a": 4, "\u767d": 4, "\u795d": 2, "\u798f": 2, "\uff01": 2, "\u9891": 2, "\u8f6c": 2, "\u4eab": 3, "\u8d77": 2, "\u6bd4": 3, "\u5fc3": 2, "\u5e74": 2, "\u6765": 2, "\u8f83": 3, "\u4efb": 3, "\u52a1": 3, "\u578b": 9, "\u8bdd": 3, "\u7814": 2, "\u7a76": 2, "\u8981": 5, "\u7aef": 2, "\u6846": 4, "\u67b6": 5, "\u57fa": 3, "\u672c": 5, "\u4f20": 3, "\u7edf": 4, "\u7b97": 3, "\u6cd5": 4, "\u2014": 2, "\u8bed": 9, "\u8a00": 8, "\u7406": 5, "\u89e3": 4, "\u6a21": 12, "\u5757": 6, "\uff08": 2, "S": 2, "o": 8, "e": 19, "n": 18, "L": 2, "a": 17, "g": 10, "u": 6, "d": 5, "r": 7, "s": 4, "t": 8, "i": 5, "(": 2, "D": 4, "l": 3, "M": 2, "m": 2, ")": 2, "\u81ea": 3, "\u7136": 3, "\u6709": 2, "\u522b": 2, "\u4e9b": 2, "\u7c7b": 2, "q": 2, "c": 4, "\u5408": 2, "\u8bc6": 2, "\u7bc7": 2, "\u662f": 2, "\u8fc7": 2, "\u6807": 2, "\u5f88": 2, "\u53ef": 2, "\u7d22": 2, "\u6b63": 2, "\u6587": 5, "\u7740": 2, "\u91cd": 3, "\u4e8e": 4, "\u62fc": 6, "\u5199": 6, "\u9519": 7, "\u8bef": 2, "\u7ea0": 6, "\u4f5c": 2}, {"4": "8", "5": " ", "6": "\u6708", "7": "2", "8": "\u65e5", "9": "\uff0c", "10": "\u7f51", "11": "\u6599", "12": "\u79f0", "13": "\u534e", "14": "\u4f4f", "15": "\u96c6", "16": "\u56e2", "17": "\u65d7", "18": "\u4e0b", "19": "\u9152", "20": "\u5e97", "21": "\u7528", "22": "\u6237", "23": "\u6570", "24": "\u636e", "25": "\u7591", "26": "\u4f3c", "27": "\u53d1", "28": "\u751f", "29": "\u6cc4", "30": "\u9732", "31": "\u3002", "32": "\u5356", "33": "\u5bb6", "34": "\u7684", "35": "\u5185", "36": "\u770b", "37": "\u5305", "38": "\u3001", "39": "\u7b49", "40": "1", "41": "0", "42": "\u4e2a", "43": "\u5ba2", "44": "\u4fe1", "45": "\u606f", "46": "\u6ce8", "47": "\u5165", "48": "\u767b", "49": "\u8bb0", "50": "\u8eab", "51": "\u4efd", "52": "\u5f00", "53": "\u5f55", "54": "\u53f7", "55": "\u8bc1", "56": "\u5bf9", "57": "\u8fd9", "58": "\u7ea6", "59": "5", "60": "\u6761", "61": "\u6253", "62": "\u51fa", "63": "\u552e", "64": "\u7b2c", "65": "\u4e09", "66": "\u65b9", "67": "\u63d0", "68": "\u8fdb", "69": "\u884c", "70": "\u9a8c", "71": "\u4e3a", "72": "\u771f", "73": "\u5b9e", "74": "\u6027", "75": "\u9ad8", "76": "\u5f53", "77": "\u660e", "78": "\u5df2", "79": "\u5728", "80": "\u5c55", "81": "\u67e5", "82": "\u4e00", "83": "\u65f6", "84": "\u95f4", "85": "\u62a5", "86": "\u8b66", "87": "\u4e0a", "88": "\u6d77", "89": "\u5230", "90": "\u4ecb", "91": "\u4f53", "92": "\u5317", "93": "\u4eac", "94": "6", "95": "N", "96": "B", "97": "A", "98": "\u4e2d", "99": "\u56fd", "100": "\u8d5b", "101": "\u5e7f", "102": "\u5dde", "103": "\u7ad9", "104": "\u5982", "105": ",", "106": "\u706b", "107": "\u7bad", "108": "\u518d", "109": "\u6b21", "110": "\u80dc", "111": "\u4ee5", "112": "9", "113": "-", "114": "\u51fb", "115": "\u8d25", "116": "\u7bee", "117": "\u59da", "118": "\u6e10", "119": "\u4f73", "120": "\u5883", "121": "\u4e86", "122": "\u5206", "123": "3", "124": "\u79d2", "125": "\u6295", "126": "\u62ff", "127": "\u677f", "128": "\u4ed6", "129": "\u8fd8", "130": "\u76d6", "131": "\u5e3d", "132": "\u4e24", "133": "\u6218", "134": "\u7686", "135": "\u7ee9", "136": "\u5706", "137": "\u6ee1", "138": "\u7ed3", "139": "\u675f", "140": "\u76f4", "141": "\uff1a", "142": "\u201c", "143": "\u6211", "144": "\u548c", "145": "\u7956", "146": "\u523b", "147": "\u4e5f", "148": "\u4e0d", "149": "\u80fd", "150": "\u5272", "151": "\u2026", "152": "\u201d", "153": "\u5143", "154": "\u65e6", "155": "\u524d", "156": "\u5915", "157": "\u535a", "158": "\u7269", "159": "\u9986", "160": "\u592e", "161": "\u89c6", "162": "\u4e3b", "163": "\u64ad", "164": "\u5eb7", "165": "\u8f89", "166": "\u971e", "167": "\u5965", "168": "\u8fd0", "169": "\u5065", "170": "\u513f", "171": "\u5085", "172": "\u56ed", "173": "\u6167", "174": "\u82cf", "175": "\u70b3", "176": "\u6dfb", "177": "\u540c", "178": "\u5531", "179": "\u54cd", "180": "\u300a", "181": "\u300b", "182": "\u5411", "183": "\u732e", "184": "\u6700", "185": "\u6df1", "186": "\u60c5", "187": "\u544a", "188": "\u767d", "189": "\u795d", "190": "\u798f", "191": "\uff01", "192": "\u9891", "193": "\u8f6c", "194": "\u4eab", "195": "\u8d77", "196": "\u6bd4", "197": "\u5fc3", "198": "\u5e74", "199": "\u6765", "200": "\u8f83", "201": "\u4efb", "202": "\u52a1", "203": "\u578b", "204": "\u8bdd", "205": "\u7814", "206": "\u7a76", "207": "\u8981", "208": "\u7aef", "209": "\u6846", "210": "\u67b6", "211": "\u57fa", "212": "\u672c", "213": "\u4f20", "214": "\u7edf", "215": "\u7b97", "216": "\u6cd5", "217": "\u2014", "218": "\u8bed", "219": "\u8a00", "220": "\u7406", "221": "\u89e3", "222": "\u6a21", "223": "\u5757", "224": "\uff08", "225": "S", "226": "o", "227": "e", "228": "n", "229": "L", "230": "a", "231": "g", "232": "u", "233": "d", "234": "r", "235": "s", "236": "t", "237": "i", "238": "(", "239": "D", "240": "l", "241": "M", "242": "m", "243": ")", "244": "\u81ea", "245": "\u7136", "246": "\u6709", "247": "\u522b", "248": "\u4e9b", "249": "\u7c7b", "250": "q", "251": "c", "252": "\u5408", "253": "\u8bc6", "254": "\u7bc7", "255": "\u662f", "256": "\u8fc7", "257": "\u6807", "258": "\u5f88", "259": "\u53ef", "260": "\u7d22", "261": "\u6b63", "262": "\u6587", "263": "\u7740", "264": "\u91cd", "265": "\u4e8e", "266": "\u62fc", "267": "\u5199", "268": "\u9519", "269": "\u8bef", "270": "\u7ea0", "271": "\u4f5c"}, {"8": 4, " ": 5, "\u6708": 6, "2": 7, "\u65e5": 8, "\uff0c": 9, "\u7f51": 10, "\u6599": 11, "\u79f0": 12, "\u534e": 13, "\u4f4f": 14, "\u96c6": 15, "\u56e2": 16, "\u65d7": 17, "\u4e0b": 18, "\u9152": 19, "\u5e97": 20, "\u7528": 21, "\u6237": 22, "\u6570": 23, "\u636e": 24, "\u7591": 25, "\u4f3c": 26, "\u53d1": 27, "\u751f": 28, "\u6cc4": 29, "\u9732": 30, "\u3002": 31, "\u5356": 32, "\u5bb6": 33, "\u7684": 34, "\u5185": 35, "\u770b": 36, "\u5305": 37, "\u3001": 38, "\u7b49": 39, "1": 40, "0": 41, "\u4e2a": 42, "\u5ba2": 43, "\u4fe1": 44, "\u606f": 45, "\u6ce8": 46, "\u5165": 47, "\u767b": 48, "\u8bb0": 49, "\u8eab": 50, "\u4efd": 51, "\u5f00": 52, "\u5f55": 53, "\u53f7": 54, "\u8bc1": 55, "\u5bf9": 56, "\u8fd9": 57, "\u7ea6": 58, "5": 59, "\u6761": 60, "\u6253": 61, "\u51fa": 62, "\u552e": 63, "\u7b2c": 64, "\u4e09": 65, "\u65b9": 66, "\u63d0": 67, "\u8fdb": 68, "\u884c": 69, "\u9a8c": 70, "\u4e3a": 71, "\u771f": 72, "\u5b9e": 73, "\u6027": 74, "\u9ad8": 75, "\u5f53": 76, "\u660e": 77, "\u5df2": 78, "\u5728": 79, "\u5c55": 80, "\u67e5": 81, "\u4e00": 82, "\u65f6": 83, "\u95f4": 84, "\u62a5": 85, "\u8b66": 86, "\u4e0a": 87, "\u6d77": 88, "\u5230": 89, "\u4ecb": 90, "\u4f53": 91, "\u5317": 92, "\u4eac": 93, "6": 94, "N": 95, "B": 96, "A": 97, "\u4e2d": 98, "\u56fd": 99, "\u8d5b": 100, "\u5e7f": 101, "\u5dde": 102, "\u7ad9": 103, "\u5982": 104, ",": 105, "\u706b": 106, "\u7bad": 107, "\u518d": 108, "\u6b21": 109, "\u80dc": 110, "\u4ee5": 111, "9": 112, "-": 113, "\u51fb": 114, "\u8d25": 115, "\u7bee": 116, "\u59da": 117, "\u6e10": 118, "\u4f73": 119, "\u5883": 120, "\u4e86": 121, "\u5206": 122, "3": 123, "\u79d2": 124, "\u6295": 125, "\u62ff": 126, "\u677f": 127, "\u4ed6": 128, "\u8fd8": 129, "\u76d6": 130, "\u5e3d": 131, "\u4e24": 132, "\u6218": 133, "\u7686": 134, "\u7ee9": 135, "\u5706": 136, "\u6ee1": 137, "\u7ed3": 138, "\u675f": 139, "\u76f4": 140, "\uff1a": 141, "\u201c": 142, "\u6211": 143, "\u548c": 144, "\u7956": 145, "\u523b": 146, "\u4e5f": 147, "\u4e0d": 148, "\u80fd": 149, "\u5272": 150, "\u2026": 151, "\u201d": 152, "\u5143": 153, "\u65e6": 154, "\u524d": 155, "\u5915": 156, "\u535a": 157, "\u7269": 158, "\u9986": 159, "\u592e": 160, "\u89c6": 161, "\u4e3b": 162, "\u64ad": 163, "\u5eb7": 164, "\u8f89": 165, "\u971e": 166, "\u5965": 167, "\u8fd0": 168, "\u5065": 169, "\u513f": 170, "\u5085": 171, "\u56ed": 172, "\u6167": 173, "\u82cf": 174, "\u70b3": 175, "\u6dfb": 176, "\u540c": 177, "\u5531": 178, "\u54cd": 179, "\u300a": 180, "\u300b": 181, "\u5411": 182, "\u732e": 183, "\u6700": 184, "\u6df1": 185, "\u60c5": 186, "\u544a": 187, "\u767d": 188, "\u795d": 189, "\u798f": 190, "\uff01": 191, "\u9891": 192, "\u8f6c": 193, "\u4eab": 194, "\u8d77": 195, "\u6bd4": 196, "\u5fc3": 197, "\u5e74": 198, "\u6765": 199, "\u8f83": 200, "\u4efb": 201, "\u52a1": 202, "\u578b": 203, "\u8bdd": 204, "\u7814": 205, "\u7a76": 206, "\u8981": 207, "\u7aef": 208, "\u6846": 209, "\u67b6": 210, "\u57fa": 211, "\u672c": 212, "\u4f20": 213, "\u7edf": 214, "\u7b97": 215, "\u6cd5": 216, "\u2014": 217, "\u8bed": 218, "\u8a00": 219, "\u7406": 220, "\u89e3": 221, "\u6a21": 222, "\u5757": 223, "\uff08": 224, "S": 225, "o": 226, "e": 227, "n": 228, "L": 229, "a": 230, "g": 231, "u": 232, "d": 233, "r": 234, "s": 235, "t": 236, "i": 237, "(": 238, "D": 239, "l": 240, "M": 241, "m": 242, ")": 243, "\u81ea": 244, "\u7136": 245, "\u6709": 246, "\u522b": 247, "\u4e9b": 248, "\u7c7b": 249, "q": 250, "c": 251, "\u5408": 252, "\u8bc6": 253, "\u7bc7": 254, "\u662f": 255, "\u8fc7": 256, "\u6807": 257, "\u5f88": 258, "\u53ef": 259, "\u7d22": 260, "\u6b63": 261, "\u6587": 262, "\u7740": 263, "\u91cd": 264, "\u4e8e": 265, "\u62fc": 266, "\u5199": 267, "\u9519": 268, "\u8bef": 269, "\u7ea0": 270, "\u4f5c": 271}]